{
  "sourceUrl": "https://ucirvinesports.com/sports/baseball/roster",
  "fetchedAt": "2026-02-27T15:38:17.448Z",
  "pageTitle": "2026 Baseball Roster - UCI Athletics",
  "teamName": "UC Irvine",
  "sport": "Baseball",
  "season": "2026",
  "playerCount": 40,
  "parser": {
    "strategy": "profile-links",
    "candidateRecords": 200,
    "dedupedRecords": 40
  },
  "players": [
    {
      "key": "https://ucirvinesports.com/sports/baseball/roster/theo-kim/7589",
      "profileUrl": "https://ucirvinesports.com/sports/baseball/roster/theo-kim/7589",
      "name": "Theo Kim",
      "firstName": "Theo",
      "lastName": "Kim",
      "number": "1",
      "photoUrl": "https://ucirvinesports.com/images/2025/10/9/1kim26.jpg?width=80&quality=90",
      "position": "INF",
      "classYear": "Sophomore",
      "height": "6-2",
      "weight": "205",
      "bats": "S",
      "throws": "R",
      "hometown": "Rancho Bernardo, Calif.",
      "from": "Rancho Bernardo, Calif.",
      "lastSchool": null,
      "previousSchool": null,
      "previousSchools": [],
      "sourceFields": {
        "B/T": "S/R",
        "Class": "Sophomore",
        "Hometown": "Rancho Bernardo, Calif.",
        "Ht./Wt.": "6-2 / 205",
        "Major": "Business Administration",
        "Position": "INF"
      }
    },
    {
      "key": "https://ucirvinesports.com/sports/baseball/roster/tommy-farmer/7599",
      "profileUrl": "https://ucirvinesports.com/sports/baseball/roster/tommy-farmer/7599",
      "name": "Tommy Farmer",
      "firstName": "Tommy",
      "lastName": "Farmer",
      "number": "2",
      "photoUrl": "https://ucirvinesports.com/images/2025/10/9/2farmeriv26.jpg?width=80&quality=90",
      "position": "OF",
      "classYear": "Junior",
      "height": "6-3",
      "weight": "210",
      "bats": "R",
      "throws": "R",
      "hometown": "Santa Monica, Calif.",
      "from": "Santa Monica, Calif.",
      "lastSchool": null,
      "previousSchool": "University of Texas",
      "previousSchools": [
        "University of Texas"
      ],
      "sourceFields": {
        "B/T": "R/R",
        "Class": "Junior",
        "Hometown": "Santa Monica, Calif.",
        "Ht./Wt.": "6-3 / 210",
        "Major": "Sociology",
        "Position": "OF",
        "Prev School": "University of Texas"
      }
    },
    {
      "key": "https://ucirvinesports.com/sports/baseball/roster/davis-d-errico/7579",
      "profileUrl": "https://ucirvinesports.com/sports/baseball/roster/davis-d-errico/7579",
      "name": "Davis D Errico",
      "firstName": "Davis D",
      "lastName": "Errico",
      "number": "4",
      "photoUrl": "https://ucirvinesports.com/images/2025/10/9/4derrico26.jpg?width=80&quality=90",
      "position": "OF",
      "classYear": "Sophomore",
      "height": "5-11",
      "weight": "195",
      "bats": "R",
      "throws": "R",
      "hometown": "Los Alamitos, Calif.",
      "from": "Los Alamitos, Calif.",
      "lastSchool": null,
      "previousSchool": null,
      "previousSchools": [],
      "sourceFields": {
        "B/T": "R/R",
        "Class": "Sophomore",
        "Hometown": "Los Alamitos, Calif.",
        "Ht./Wt.": "5-11 / 195",
        "Major": "Undeclared",
        "Position": "OF"
      }
    },
    {
      "key": "https://ucirvinesports.com/sports/baseball/roster/james-castagnola/7577",
      "profileUrl": "https://ucirvinesports.com/sports/baseball/roster/james-castagnola/7577",
      "name": "James Castagnola",
      "firstName": "James",
      "lastName": "Castagnola",
      "number": "5",
      "photoUrl": "https://ucirvinesports.com/images/2025/10/9/5castagnola26.jpg?width=80&quality=90",
      "position": "INF",
      "classYear": "Redshirt Junior",
      "height": "6-1",
      "weight": "195",
      "bats": "R",
      "throws": "R",
      "hometown": "San Diego, Calif.",
      "from": "San Diego, Calif.",
      "lastSchool": null,
      "previousSchool": null,
      "previousSchools": [],
      "sourceFields": {
        "B/T": "R/R",
        "Class": "Redshirt Junior",
        "Hometown": "San Diego, Calif.",
        "Ht./Wt.": "6-1 / 195",
        "Major": "Business Economics",
        "Position": "INF"
      }
    },
    {
      "key": "https://ucirvinesports.com/sports/baseball/roster/dylan-hillman/7600",
      "profileUrl": "https://ucirvinesports.com/sports/baseball/roster/dylan-hillman/7600",
      "name": "Dylan Hillman",
      "firstName": "Dylan",
      "lastName": "Hillman",
      "number": "8",
      "photoUrl": "https://ucirvinesports.com/images/2025/10/9/8hillman26.jpg?width=80&quality=90",
      "position": "INF",
      "classYear": "Sophomore",
      "height": "5-11",
      "weight": "180",
      "bats": "R",
      "throws": "R",
      "hometown": "Danville, Calif.",
      "from": "Danville, Calif.",
      "lastSchool": null,
      "previousSchool": "College of San Mateo",
      "previousSchools": [
        "College of San Mateo"
      ],
      "sourceFields": {
        "B/T": "R/R",
        "Class": "Sophomore",
        "Hometown": "Danville, Calif.",
        "Ht./Wt.": "5-11 / 180",
        "Major": "Sociology",
        "Position": "INF",
        "Prev School": "College of San Mateo"
      }
    },
    {
      "key": "https://ucirvinesports.com/sports/baseball/roster/rowan-felsch/7581",
      "profileUrl": "https://ucirvinesports.com/sports/baseball/roster/rowan-felsch/7581",
      "name": "Rowan Felsch",
      "firstName": "Rowan",
      "lastName": "Felsch",
      "number": "9",
      "photoUrl": "https://ucirvinesports.com/images/2025/10/9/9felsch26.jpg?width=80&quality=90",
      "position": "OF",
      "classYear": "Senior",
      "height": "6-2",
      "weight": "200",
      "bats": "L",
      "throws": "L",
      "hometown": "Palo Alto, Calif.",
      "from": "Palo Alto, Calif.",
      "lastSchool": null,
      "previousSchool": "College of San Mateo",
      "previousSchools": [
        "College of San Mateo"
      ],
      "sourceFields": {
        "B/T": "L/L",
        "Class": "Senior",
        "Hometown": "Palo Alto, Calif.",
        "Ht./Wt.": "6-2 / 200",
        "Major": "Psychological Sciences",
        "Position": "OF",
        "Prev School": "College of San Mateo"
      }
    },
    {
      "key": "https://ucirvinesports.com/sports/baseball/roster/zach-doyle/7580",
      "profileUrl": "https://ucirvinesports.com/sports/baseball/roster/zach-doyle/7580",
      "name": "Zach Doyle",
      "firstName": "Zach",
      "lastName": "Doyle",
      "number": "10",
      "photoUrl": "https://ucirvinesports.com/images/2025/10/9/10doyle26.jpg?width=80&quality=90",
      "position": "OF",
      "classYear": "Redshirt Freshman",
      "height": "5-10",
      "weight": "180",
      "bats": "L",
      "throws": "L",
      "hometown": "Ladera Ranch, Calif.",
      "from": "Ladera Ranch, Calif.",
      "lastSchool": null,
      "previousSchool": null,
      "previousSchools": [],
      "sourceFields": {
        "B/T": "L/L",
        "Class": "Redshirt Freshman",
        "Hometown": "Ladera Ranch, Calif.",
        "Ht./Wt.": "5-10 / 180",
        "Major": "Undeclared",
        "Position": "OF"
      }
    },
    {
      "key": "https://ucirvinesports.com/sports/baseball/roster/jack-ross/7594",
      "profileUrl": "https://ucirvinesports.com/sports/baseball/roster/jack-ross/7594",
      "name": "Jack Ross",
      "firstName": "Jack",
      "lastName": "Ross",
      "number": "11",
      "photoUrl": "https://ucirvinesports.com/images/2025/10/9/11ross26.jpg?width=80&quality=90",
      "position": "RHP",
      "classYear": "Senior",
      "height": "6-3",
      "weight": "200",
      "bats": "R",
      "throws": "R",
      "hometown": "Huntington Beach, Calif.",
      "from": "Huntington Beach, Calif.",
      "lastSchool": null,
      "previousSchool": "Orange Coast College",
      "previousSchools": [
        "Orange Coast College"
      ],
      "sourceFields": {
        "B/T": "R/R",
        "Class": "Senior",
        "Hometown": "Huntington Beach, Calif.",
        "Ht./Wt.": "6-3 / 200",
        "Major": "Education",
        "Position": "RHP",
        "Prev School": "Orange Coast College"
      }
    },
    {
      "key": "https://ucirvinesports.com/sports/baseball/roster/kai-smith/7606",
      "profileUrl": "https://ucirvinesports.com/sports/baseball/roster/kai-smith/7606",
      "name": "Kai Smith",
      "firstName": "Kai",
      "lastName": "Smith",
      "number": "12",
      "photoUrl": "https://ucirvinesports.com/images/2026/1/30/12smith26.jpg?width=80&quality=90",
      "position": "OF",
      "classYear": "Redshirt Sophomore",
      "height": "6-0",
      "weight": "190",
      "bats": "R",
      "throws": "R",
      "hometown": "Danville, Calif.",
      "from": "Danville, Calif.",
      "lastSchool": null,
      "previousSchool": "Los Medanos College",
      "previousSchools": [
        "Los Medanos College"
      ],
      "sourceFields": {
        "B/T": "R/R",
        "Class": "Redshirt Sophomore",
        "Hometown": "Danville, Calif.",
        "Ht./Wt.": "6-0 / 190",
        "Major": "Sociology",
        "Position": "OF",
        "Prev School": "Los Medanos College"
      }
    },
    {
      "key": "https://ucirvinesports.com/sports/baseball/roster/ricky-ojeda/7591",
      "profileUrl": "https://ucirvinesports.com/sports/baseball/roster/ricky-ojeda/7591",
      "name": "Ricky Ojeda",
      "firstName": "Ricky",
      "lastName": "Ojeda",
      "number": "13",
      "photoUrl": "https://ucirvinesports.com/images/2025/10/9/13ojeda26.jpg?width=80&quality=90",
      "position": "LHP",
      "classYear": "Junior",
      "height": "5-11",
      "weight": "185",
      "bats": "L",
      "throws": "L",
      "hometown": "Valencia, Calif.",
      "from": "Valencia, Calif.",
      "lastSchool": null,
      "previousSchool": null,
      "previousSchools": [],
      "sourceFields": {
        "B/T": "L/L",
        "Class": "Junior",
        "Hometown": "Valencia, Calif.",
        "Ht./Wt.": "5-11 / 185",
        "Major": "Business Economics",
        "Position": "LHP"
      }
    },
    {
      "key": "https://ucirvinesports.com/sports/baseball/roster/danny-suarez/7595",
      "profileUrl": "https://ucirvinesports.com/sports/baseball/roster/danny-suarez/7595",
      "name": "Danny Suarez",
      "firstName": "Danny",
      "lastName": "Suarez",
      "number": "14",
      "photoUrl": "https://ucirvinesports.com/images/2025/10/9/14suarez26.jpg?width=80&quality=90",
      "position": "RHP",
      "classYear": "Redshirt Senior",
      "height": "6-3",
      "weight": "210",
      "bats": "R",
      "throws": "R",
      "hometown": "Trabuco Canyon, Calif.",
      "from": "Trabuco Canyon, Calif.",
      "lastSchool": null,
      "previousSchool": null,
      "previousSchools": [],
      "sourceFields": {
        "B/T": "R/R",
        "Class": "Redshirt Senior",
        "Hometown": "Trabuco Canyon, Calif.",
        "Ht./Wt.": "6-3 / 210",
        "Major": "Sociology",
        "Position": "RHP"
      }
    },
    {
      "key": "https://ucirvinesports.com/sports/baseball/roster/finnegan-wall/7596",
      "profileUrl": "https://ucirvinesports.com/sports/baseball/roster/finnegan-wall/7596",
      "name": "Finnegan Wall",
      "firstName": "Finnegan",
      "lastName": "Wall",
      "number": "15",
      "photoUrl": "https://ucirvinesports.com/images/2025/10/9/15wall26.jpg?width=80&quality=90",
      "position": "RHP",
      "classYear": "Redshirt Senior",
      "height": "6-2",
      "weight": "205",
      "bats": "R",
      "throws": "R",
      "hometown": "Hesperia, Calif.",
      "from": "Hesperia, Calif.",
      "lastSchool": null,
      "previousSchool": null,
      "previousSchools": [],
      "sourceFields": {
        "B/T": "R/R",
        "Class": "Redshirt Senior",
        "Hometown": "Hesperia, Calif.",
        "Ht./Wt.": "6-2 / 205",
        "Major": "Psychological Sciences",
        "Position": "RHP"
      }
    },
    {
      "key": "https://ucirvinesports.com/sports/baseball/roster/michael-podstreleny/7592",
      "profileUrl": "https://ucirvinesports.com/sports/baseball/roster/michael-podstreleny/7592",
      "name": "Michael Podstreleny",
      "firstName": "Michael",
      "lastName": "Podstreleny",
      "number": "16",
      "photoUrl": "https://ucirvinesports.com/images/2025/10/9/16podstreleny26.jpg?width=80&quality=90",
      "position": "C",
      "classYear": "Redshirt Freshman",
      "height": "5-11",
      "weight": "190",
      "bats": "L",
      "throws": "R",
      "hometown": "San Diego, Calif.",
      "from": "San Diego, Calif.",
      "lastSchool": null,
      "previousSchool": null,
      "previousSchools": [],
      "sourceFields": {
        "B/T": "L/R",
        "Class": "Redshirt Freshman",
        "Hometown": "San Diego, Calif.",
        "Ht./Wt.": "5-11 / 190",
        "Major": "Undeclared",
        "Position": "C"
      }
    },
    {
      "key": "https://ucirvinesports.com/sports/baseball/roster/dane-grant/7586",
      "profileUrl": "https://ucirvinesports.com/sports/baseball/roster/dane-grant/7586",
      "name": "Dane Grant",
      "firstName": "Dane",
      "lastName": "Grant",
      "number": "17",
      "photoUrl": "https://ucirvinesports.com/images/2025/10/9/17grant26.jpg?width=80&quality=90",
      "position": "LHP",
      "classYear": "Redshirt Freshman",
      "height": "6-2",
      "weight": "185",
      "bats": "L",
      "throws": "L",
      "hometown": "San Juan Capistrano, Calif.",
      "from": "San Juan Capistrano, Calif.",
      "lastSchool": null,
      "previousSchool": null,
      "previousSchools": [],
      "sourceFields": {
        "B/T": "L/L",
        "Class": "Redshirt Freshman",
        "Hometown": "San Juan Capistrano, Calif.",
        "Ht./Wt.": "6-2 / 185",
        "Major": "Undeclared",
        "Position": "LHP"
      }
    },
    {
      "key": "https://ucirvinesports.com/sports/baseball/roster/zach-crandall/7578",
      "profileUrl": "https://ucirvinesports.com/sports/baseball/roster/zach-crandall/7578",
      "name": "Zach Crandall",
      "firstName": "Zach",
      "lastName": "Crandall",
      "number": "18",
      "photoUrl": "https://ucirvinesports.com/images/2025/10/9/18crandall26.jpg?width=80&quality=90",
      "position": "C",
      "classYear": "Redshirt Senior",
      "height": "6-0",
      "weight": "200",
      "bats": "R",
      "throws": "R",
      "hometown": "Ladera Ranch, Calif.",
      "from": "Ladera Ranch, Calif.",
      "lastSchool": null,
      "previousSchool": "University of Utah",
      "previousSchools": [
        "University of Utah"
      ],
      "sourceFields": {
        "B/T": "R/R",
        "Class": "Redshirt Senior",
        "Hometown": "Ladera Ranch, Calif.",
        "Ht./Wt.": "6-0 / 200",
        "Major": "Sociology",
        "Position": "C",
        "Prev School": "University of Utah"
      }
    },
    {
      "key": "https://ucirvinesports.com/sports/baseball/roster/tim-grack/7585",
      "profileUrl": "https://ucirvinesports.com/sports/baseball/roster/tim-grack/7585",
      "name": "Tim Grack",
      "firstName": "Tim",
      "lastName": "Grack",
      "number": "20",
      "photoUrl": "https://ucirvinesports.com/images/2025/10/9/20grack26_TDxu0.jpg?width=80&quality=90",
      "position": "RHP",
      "classYear": "Redshirt Sophomore",
      "height": "6-1",
      "weight": "195",
      "bats": "R",
      "throws": "R",
      "hometown": "Fountain Valley, Calif.",
      "from": "Fountain Valley, Calif.",
      "lastSchool": null,
      "previousSchool": null,
      "previousSchools": [],
      "sourceFields": {
        "B/T": "R/R",
        "Class": "Redshirt Sophomore",
        "Hometown": "Fountain Valley, Calif.",
        "Ht./Wt.": "6-1 / 195",
        "Major": "Business Economics",
        "Position": "RHP"
      }
    },
    {
      "key": "https://ucirvinesports.com/sports/baseball/roster/landon-gaz/7584",
      "profileUrl": "https://ucirvinesports.com/sports/baseball/roster/landon-gaz/7584",
      "name": "Landon Gaz",
      "firstName": "Landon",
      "lastName": "Gaz",
      "number": "21",
      "photoUrl": "https://ucirvinesports.com/images/2025/10/9/21gaz26_5NSXV.jpg?width=80&quality=90",
      "position": "1B/OF",
      "classYear": "Junior",
      "height": "6-2",
      "weight": "235",
      "bats": "R",
      "throws": "R",
      "hometown": "Moorpark, Calif.",
      "from": "Moorpark, Calif.",
      "lastSchool": null,
      "previousSchool": null,
      "previousSchools": [],
      "sourceFields": {
        "B/T": "R/R",
        "Class": "Junior",
        "Hometown": "Moorpark, Calif.",
        "Ht./Wt.": "6-2 / 235",
        "Major": "Social Ecology",
        "Position": "1B/OF"
      }
    },
    {
      "key": "https://ucirvinesports.com/sports/baseball/roster/david-butler/7575",
      "profileUrl": "https://ucirvinesports.com/sports/baseball/roster/david-butler/7575",
      "name": "David Butler",
      "firstName": "David",
      "lastName": "Butler",
      "number": "22",
      "photoUrl": "https://ucirvinesports.com/images/2025/10/9/22butler26.jpg?width=80&quality=90",
      "position": "RHP",
      "classYear": "Fifth Year",
      "height": "6-1",
      "weight": "185",
      "bats": "R",
      "throws": "R",
      "hometown": "Riverside, Calif.",
      "from": "Riverside, Calif.",
      "lastSchool": null,
      "previousSchool": "Riverside City College",
      "previousSchools": [
        "Riverside City College"
      ],
      "sourceFields": {
        "B/T": "R/R",
        "Class": "Fifth Year",
        "Hometown": "Riverside, Calif.",
        "Ht./Wt.": "6-1 / 185",
        "Major": "Sociology",
        "Position": "RHP",
        "Prev School": "Riverside City College"
      }
    },
    {
      "key": "https://ucirvinesports.com/sports/baseball/roster/frankie-carney/7576",
      "profileUrl": "https://ucirvinesports.com/sports/baseball/roster/frankie-carney/7576",
      "name": "Frankie Carney",
      "firstName": "Frankie",
      "lastName": "Carney",
      "number": "23",
      "photoUrl": "https://ucirvinesports.com/images/2025/10/9/23carney26.jpg?width=80&quality=90",
      "position": "INF",
      "classYear": "Redshirt Junior",
      "height": "5-10",
      "weight": "180",
      "bats": "L",
      "throws": "R",
      "hometown": "San Diego, Calif.",
      "from": "San Diego, Calif.",
      "lastSchool": null,
      "previousSchool": null,
      "previousSchools": [],
      "sourceFields": {
        "B/T": "L/R",
        "Class": "Redshirt Junior",
        "Hometown": "San Diego, Calif.",
        "Ht./Wt.": "5-10 / 180",
        "Major": "Education",
        "Position": "INF"
      }
    },
    {
      "key": "https://ucirvinesports.com/sports/baseball/roster/auggie-gutierrez/7587",
      "profileUrl": "https://ucirvinesports.com/sports/baseball/roster/auggie-gutierrez/7587",
      "name": "Auggie Gutierrez",
      "firstName": "Auggie",
      "lastName": "Gutierrez",
      "number": "24",
      "photoUrl": "https://ucirvinesports.com/images/2025/10/9/24gutierrez26.jpg?width=80&quality=90",
      "position": "INF",
      "classYear": "Redshirt Junior",
      "height": "5-11",
      "weight": "190",
      "bats": "R",
      "throws": "R",
      "hometown": "Yorba Linda, Calif.",
      "from": "Yorba Linda, Calif.",
      "lastSchool": null,
      "previousSchool": null,
      "previousSchools": [],
      "sourceFields": {
        "B/T": "R/R",
        "Class": "Redshirt Junior",
        "Hometown": "Yorba Linda, Calif.",
        "Ht./Wt.": "5-11 / 190",
        "Major": "Mechanical Engineering",
        "Position": "INF"
      }
    },
    {
      "key": "https://ucirvinesports.com/sports/baseball/roster/alonso-reyes/7593",
      "profileUrl": "https://ucirvinesports.com/sports/baseball/roster/alonso-reyes/7593",
      "name": "Alonso Reyes",
      "firstName": "Alonso",
      "lastName": "Reyes",
      "number": "25",
      "photoUrl": "https://ucirvinesports.com/images/2025/10/9/25reyes26.jpg?width=80&quality=90",
      "position": "1B/C",
      "classYear": "Redshirt Junior",
      "height": "6-0",
      "weight": "195",
      "bats": "L",
      "throws": "R",
      "hometown": "Inglewood, Calif.",
      "from": "Inglewood, Calif.",
      "lastSchool": null,
      "previousSchool": "Cerritos College",
      "previousSchools": [
        "Cerritos College"
      ],
      "sourceFields": {
        "B/T": "L/R",
        "Class": "Redshirt Junior",
        "Hometown": "Inglewood, Calif.",
        "Ht./Wt.": "6-0 / 195",
        "Major": "Psychological Sciences",
        "Position": "1B/C",
        "Prev School": "Cerritos College"
      }
    },
    {
      "key": "https://ucirvinesports.com/sports/baseball/roster/noah-alvarez/7612",
      "profileUrl": "https://ucirvinesports.com/sports/baseball/roster/noah-alvarez/7612",
      "name": "Noah Alvarez",
      "firstName": "Noah",
      "lastName": "Alvarez",
      "number": "26",
      "photoUrl": "https://ucirvinesports.com/images/2025/10/9/26alvarez26_N1U6Y.jpg?width=80&quality=90",
      "position": "INF",
      "classYear": "Junior",
      "height": "6-2",
      "weight": "180",
      "bats": "L",
      "throws": "R",
      "hometown": "Chino, Calif.",
      "from": "Chino, Calif.",
      "lastSchool": null,
      "previousSchool": "Cal State Bakersfield",
      "previousSchools": [
        "Cal State Bakersfield"
      ],
      "sourceFields": {
        "B/T": "L/R",
        "Class": "Junior",
        "Hometown": "Chino, Calif.",
        "Ht./Wt.": "6-2 / 180",
        "Major": "Education",
        "Position": "INF",
        "Prev School": "Cal State Bakersfield"
      }
    },
    {
      "key": "https://ucirvinesports.com/sports/baseball/roster/brandon-luu/7590",
      "profileUrl": "https://ucirvinesports.com/sports/baseball/roster/brandon-luu/7590",
      "name": "Brandon Luu",
      "firstName": "Brandon",
      "lastName": "Luu",
      "number": "27",
      "photoUrl": "https://ucirvinesports.com/images/2025/10/9/27luu26.jpg?width=80&quality=90",
      "position": "LHP",
      "classYear": "Redshirt Sophomore",
      "height": "6-2",
      "weight": "205",
      "bats": "L",
      "throws": "L",
      "hometown": "Irvine, Calif.",
      "from": "Irvine, Calif.",
      "lastSchool": null,
      "previousSchool": null,
      "previousSchools": [],
      "sourceFields": {
        "B/T": "L/L",
        "Class": "Redshirt Sophomore",
        "Hometown": "Irvine, Calif.",
        "Ht./Wt.": "6-2 / 205",
        "Major": "Psychology",
        "Position": "LHP"
      }
    },
    {
      "key": "https://ucirvinesports.com/sports/baseball/roster/trevor-hansen/7588",
      "profileUrl": "https://ucirvinesports.com/sports/baseball/roster/trevor-hansen/7588",
      "name": "Trevor Hansen",
      "firstName": "Trevor",
      "lastName": "Hansen",
      "number": "28",
      "photoUrl": "https://ucirvinesports.com/images/2025/10/9/28hansen26.jpg?width=80&quality=90",
      "position": "RHP",
      "classYear": "Junior",
      "height": "6-2",
      "weight": "195",
      "bats": "R",
      "throws": "R",
      "hometown": "Simi Valley, Calif.",
      "from": "Simi Valley, Calif.",
      "lastSchool": null,
      "previousSchool": null,
      "previousSchools": [],
      "sourceFields": {
        "B/T": "R/R",
        "Class": "Junior",
        "Hometown": "Simi Valley, Calif.",
        "Ht./Wt.": "6-2 / 195",
        "Major": "Social Ecology",
        "Position": "RHP"
      }
    },
    {
      "key": "https://ucirvinesports.com/sports/baseball/roster/peyton-rodgers/7603",
      "profileUrl": "https://ucirvinesports.com/sports/baseball/roster/peyton-rodgers/7603",
      "name": "Peyton Rodgers",
      "firstName": "Peyton",
      "lastName": "Rodgers",
      "number": "30",
      "photoUrl": "https://ucirvinesports.com/images/2025/10/9/30rodgers26.jpg?width=80&quality=90",
      "position": "RHP",
      "classYear": "Sophomore",
      "height": "6-0",
      "weight": "180",
      "bats": "R",
      "throws": "R",
      "hometown": "Solana Beach, Calif.",
      "from": "Solana Beach, Calif.",
      "lastSchool": null,
      "previousSchool": "San Diego State",
      "previousSchools": [
        "San Diego State"
      ],
      "sourceFields": {
        "B/T": "R/R",
        "Class": "Sophomore",
        "Hometown": "Solana Beach, Calif.",
        "Ht./Wt.": "6-0 / 180",
        "Major": "Sociology",
        "Position": "RHP",
        "Prev School": "San Diego State"
      }
    },
    {
      "key": "https://ucirvinesports.com/sports/baseball/roster/lucas-schermer/7604",
      "profileUrl": "https://ucirvinesports.com/sports/baseball/roster/lucas-schermer/7604",
      "name": "Lucas Schermer",
      "firstName": "Lucas",
      "lastName": "Schermer",
      "number": "31",
      "photoUrl": "https://ucirvinesports.com/images/2025/10/24/31schermer26.jpg?width=80&quality=90",
      "position": "INF",
      "classYear": "Freshman",
      "height": "6-3",
      "weight": "198",
      "bats": "R",
      "throws": "R",
      "hometown": "Hermosa Beach, Calif.",
      "from": "Hermosa Beach, Calif.",
      "lastSchool": null,
      "previousSchool": null,
      "previousSchools": [],
      "sourceFields": {
        "B/T": "R/R",
        "Class": "Freshman",
        "Hometown": "Hermosa Beach, Calif.",
        "Ht./Wt.": "6-3 / 198",
        "Major": "Undeclared",
        "Position": "INF"
      }
    },
    {
      "key": "https://ucirvinesports.com/sports/baseball/roster/zane-nordquist/7602",
      "profileUrl": "https://ucirvinesports.com/sports/baseball/roster/zane-nordquist/7602",
      "name": "Zane Nordquist",
      "firstName": "Zane",
      "lastName": "Nordquist",
      "number": "32",
      "photoUrl": "https://ucirvinesports.com/images/2025/10/9/32nordquist26.jpg?width=80&quality=90",
      "position": "LHP",
      "classYear": "Freshman",
      "height": "5-11",
      "weight": "175",
      "bats": "L",
      "throws": "L",
      "hometown": "Oceanside, Calif.",
      "from": "Oceanside, Calif.",
      "lastSchool": null,
      "previousSchool": null,
      "previousSchools": [],
      "sourceFields": {
        "B/T": "L/L",
        "Class": "Freshman",
        "Hometown": "Oceanside, Calif.",
        "Ht./Wt.": "5-11 / 175",
        "Major": "Undeclared",
        "Position": "LHP"
      }
    },
    {
      "key": "https://ucirvinesports.com/sports/baseball/roster/tyler-foster/7583",
      "profileUrl": "https://ucirvinesports.com/sports/baseball/roster/tyler-foster/7583",
      "name": "Tyler Foster",
      "firstName": "Tyler",
      "lastName": "Foster",
      "number": "33",
      "photoUrl": "https://ucirvinesports.com/images/2025/10/9/33foster26.jpg?width=80&quality=90",
      "position": "RHP",
      "classYear": "Sophomore",
      "height": "6-1",
      "weight": "190",
      "bats": "R",
      "throws": "R",
      "hometown": "Carlsbad, Calif.",
      "from": "Carlsbad, Calif.",
      "lastSchool": null,
      "previousSchool": null,
      "previousSchools": [],
      "sourceFields": {
        "B/T": "R/R",
        "Class": "Sophomore",
        "Hometown": "Carlsbad, Calif.",
        "Ht./Wt.": "6-1 / 190",
        "Major": "Undeclared",
        "Position": "RHP"
      }
    },
    {
      "key": "https://ucirvinesports.com/sports/baseball/roster/cole-clark/7598",
      "profileUrl": "https://ucirvinesports.com/sports/baseball/roster/cole-clark/7598",
      "name": "Cole Clark",
      "firstName": "Cole",
      "lastName": "Clark",
      "number": "34",
      "photoUrl": "https://ucirvinesports.com/images/2025/10/9/34clark26.jpg?width=80&quality=90",
      "position": "INF",
      "classYear": "Freshman",
      "height": "6-1",
      "weight": "175",
      "bats": "L",
      "throws": "R",
      "hometown": "Huntington Beach, Calif.",
      "from": "Huntington Beach, Calif.",
      "lastSchool": null,
      "previousSchool": null,
      "previousSchools": [],
      "sourceFields": {
        "B/T": "L/R",
        "Class": "Freshman",
        "Hometown": "Huntington Beach, Calif.",
        "Ht./Wt.": "6-1 / 175",
        "Major": "Undeclared",
        "Position": "INF"
      }
    },
    {
      "key": "https://ucirvinesports.com/sports/baseball/roster/connor-dietsch/7607",
      "profileUrl": "https://ucirvinesports.com/sports/baseball/roster/connor-dietsch/7607",
      "name": "Connor Dietsch",
      "firstName": "Connor",
      "lastName": "Dietsch",
      "number": "35",
      "photoUrl": "https://ucirvinesports.com/images/2026/1/30/35dietsch26.jpg?width=80&quality=90",
      "position": "C",
      "classYear": "Redshirt Junior",
      "height": "6-3",
      "weight": "198",
      "bats": "R",
      "throws": "R",
      "hometown": "Mission Viejo, Calif.",
      "from": "Mission Viejo, Calif.",
      "lastSchool": null,
      "previousSchool": "Santa Ana College",
      "previousSchools": [
        "Santa Ana College"
      ],
      "sourceFields": {
        "B/T": "R/R",
        "Class": "Redshirt Junior",
        "Hometown": "Mission Viejo, Calif.",
        "Ht./Wt.": "6-3 / 198",
        "Major": "Sociology",
        "Position": "C",
        "Prev School": "Santa Ana College"
      }
    },
    {
      "key": "https://ucirvinesports.com/sports/baseball/roster/zach-fjelstad/7582",
      "profileUrl": "https://ucirvinesports.com/sports/baseball/roster/zach-fjelstad/7582",
      "name": "Zach Fjelstad",
      "firstName": "Zach",
      "lastName": "Fjelstad",
      "number": "36",
      "photoUrl": "https://ucirvinesports.com/images/2025/10/9/36fjelstad26.jpg?width=80&quality=90",
      "position": "INF",
      "classYear": "Junior",
      "height": "5-11",
      "weight": "190",
      "bats": "L",
      "throws": "R",
      "hometown": "Coto de Caza, Calif.",
      "from": "Coto de Caza, Calif.",
      "lastSchool": null,
      "previousSchool": "Ohio State",
      "previousSchools": [
        "Ohio State"
      ],
      "sourceFields": {
        "B/T": "L/R",
        "Class": "Junior",
        "Hometown": "Coto de Caza, Calif.",
        "Ht./Wt.": "5-11 / 190",
        "Major": "Sociology",
        "Position": "INF",
        "Prev School": "Ohio State"
      }
    },
    {
      "key": "https://ucirvinesports.com/sports/baseball/roster/julian-custer/7611",
      "profileUrl": "https://ucirvinesports.com/sports/baseball/roster/julian-custer/7611",
      "name": "Julian Custer",
      "firstName": "Julian",
      "lastName": "Custer",
      "number": "37",
      "photoUrl": "https://ucirvinesports.com/images/2025/10/9/37custer26.jpg?width=80&quality=90",
      "position": "RHP",
      "classYear": "Redshirt Sophomore",
      "height": "6-2",
      "weight": "185",
      "bats": "R",
      "throws": "R",
      "hometown": "San Diego, Calif.",
      "from": "San Diego, Calif.",
      "lastSchool": null,
      "previousSchool": "UC San Diego",
      "previousSchools": [
        "UC San Diego"
      ],
      "sourceFields": {
        "B/T": "R/R",
        "Class": "Redshirt Sophomore",
        "Hometown": "San Diego, Calif.",
        "Ht./Wt.": "6-2 / 185",
        "Major": "Business Economics",
        "Position": "RHP",
        "Prev School": "UC San Diego"
      }
    },
    {
      "key": "https://ucirvinesports.com/sports/baseball/roster/daniel-polasek/7609",
      "profileUrl": "https://ucirvinesports.com/sports/baseball/roster/daniel-polasek/7609",
      "name": "Daniel Polasek",
      "firstName": "Daniel",
      "lastName": "Polasek",
      "number": "38",
      "photoUrl": "https://ucirvinesports.com/images/2025/10/9/38polasek26.jpg?width=80&quality=90",
      "position": "OF",
      "classYear": "Sophomore",
      "height": "5-11",
      "weight": "190",
      "bats": "L",
      "throws": "R",
      "hometown": "Martinez, Calif.",
      "from": "Martinez, Calif.",
      "lastSchool": null,
      "previousSchool": "Los Medanos College",
      "previousSchools": [
        "Los Medanos College"
      ],
      "sourceFields": {
        "B/T": "L/R",
        "Class": "Sophomore",
        "Hometown": "Martinez, Calif.",
        "Ht./Wt.": "5-11 / 190",
        "Major": "Sociology",
        "Position": "OF",
        "Prev School": "Los Medanos College"
      }
    },
    {
      "key": "https://ucirvinesports.com/sports/baseball/roster/hunter-manning/7601",
      "profileUrl": "https://ucirvinesports.com/sports/baseball/roster/hunter-manning/7601",
      "name": "Hunter Manning",
      "firstName": "Hunter",
      "lastName": "Manning",
      "number": "40",
      "photoUrl": "https://ucirvinesports.com/images/2025/10/9/40manning26.jpg?width=80&quality=90",
      "position": "RHP",
      "classYear": "Freshman",
      "height": "6-5",
      "weight": "220",
      "bats": "L",
      "throws": "R",
      "hometown": "Valencia, Calif.",
      "from": "Valencia, Calif.",
      "lastSchool": null,
      "previousSchool": null,
      "previousSchools": [],
      "sourceFields": {
        "B/T": "L/R",
        "Class": "Freshman",
        "Hometown": "Valencia, Calif.",
        "Ht./Wt.": "6-5 / 220",
        "Major": "Undeclared",
        "Position": "RHP"
      }
    },
    {
      "key": "https://ucirvinesports.com/sports/baseball/roster/cade-castles/7597",
      "profileUrl": "https://ucirvinesports.com/sports/baseball/roster/cade-castles/7597",
      "name": "Cade Castles",
      "firstName": "Cade",
      "lastName": "Castles",
      "number": "41",
      "photoUrl": "https://ucirvinesports.com/images/2025/10/9/41castles26.jpg?width=80&quality=90",
      "position": "RHP",
      "classYear": "Freshman",
      "height": "6-2",
      "weight": "175",
      "bats": "R",
      "throws": "R",
      "hometown": "Davis, Calif.",
      "from": "Davis, Calif.",
      "lastSchool": null,
      "previousSchool": null,
      "previousSchools": [],
      "sourceFields": {
        "B/T": "R/R",
        "Class": "Freshman",
        "Hometown": "Davis, Calif.",
        "Ht./Wt.": "6-2 / 175",
        "Major": "Undeclared",
        "Position": "RHP"
      }
    },
    {
      "key": "https://ucirvinesports.com/sports/baseball/roster/ryder-brooks/7574",
      "profileUrl": "https://ucirvinesports.com/sports/baseball/roster/ryder-brooks/7574",
      "name": "Ryder Brooks",
      "firstName": "Ryder",
      "lastName": "Brooks",
      "number": "42",
      "photoUrl": "https://ucirvinesports.com/images/2025/10/9/42brooks26.jpg?width=80&quality=90",
      "position": "LHP",
      "classYear": "Redshirt Junior",
      "height": "6-3",
      "weight": "200",
      "bats": "L",
      "throws": "L",
      "hometown": "Fountain Valley, Calif.",
      "from": "Fountain Valley, Calif.",
      "lastSchool": null,
      "previousSchool": null,
      "previousSchools": [],
      "sourceFields": {
        "B/T": "L/L",
        "Class": "Redshirt Junior",
        "Hometown": "Fountain Valley, Calif.",
        "Ht./Wt.": "6-3 / 200",
        "Major": "Business Economics",
        "Position": "LHP"
      }
    },
    {
      "key": "https://ucirvinesports.com/sports/baseball/roster/alex-schmidt/7605",
      "profileUrl": "https://ucirvinesports.com/sports/baseball/roster/alex-schmidt/7605",
      "name": "Alex Schmidt",
      "firstName": "Alex",
      "lastName": "Schmidt",
      "number": "44",
      "photoUrl": "https://ucirvinesports.com/images/2025/10/9/44schmidt26.jpg?width=80&quality=90",
      "position": "RHP/1B",
      "classYear": "Freshman",
      "height": "6-2",
      "weight": "215",
      "bats": "R",
      "throws": "R",
      "hometown": "Sherman Oaks, Calif.",
      "from": "Sherman Oaks, Calif.",
      "lastSchool": null,
      "previousSchool": null,
      "previousSchools": [],
      "sourceFields": {
        "B/T": "R/R",
        "Class": "Freshman",
        "Hometown": "Sherman Oaks, Calif.",
        "Ht./Wt.": "6-2 / 215",
        "Major": "Mechanical Engineering",
        "Position": "RHP/1B"
      }
    },
    {
      "key": "https://ucirvinesports.com/sports/baseball/roster/jaxton-andeel/7573",
      "profileUrl": "https://ucirvinesports.com/sports/baseball/roster/jaxton-andeel/7573",
      "name": "Jaxton Andeel",
      "firstName": "Jaxton",
      "lastName": "Andeel",
      "number": "45",
      "photoUrl": "https://ucirvinesports.com/images/2025/10/9/45andeel26_lexPC.jpg?width=80&quality=90",
      "position": "LHP",
      "classYear": "Senior",
      "height": "6-4",
      "weight": "210",
      "bats": "L",
      "throws": "L",
      "hometown": "Placentia, Calif.",
      "from": "Placentia, Calif.",
      "lastSchool": null,
      "previousSchool": "Santa Ana College",
      "previousSchools": [
        "Santa Ana College"
      ],
      "sourceFields": {
        "B/T": "L/L",
        "Class": "Senior",
        "Hometown": "Placentia, Calif.",
        "Ht./Wt.": "6-4 / 210",
        "Major": "Business Economics",
        "Position": "LHP",
        "Prev School": "Santa Ana College"
      }
    },
    {
      "key": "https://ucirvinesports.com/sports/baseball/roster/efren-ortega/7608",
      "profileUrl": "https://ucirvinesports.com/sports/baseball/roster/efren-ortega/7608",
      "name": "Efren Ortega",
      "firstName": "Efren",
      "lastName": "Ortega",
      "number": "50",
      "photoUrl": "https://ucirvinesports.com/images/2025/10/9/50ortega26.jpg?width=80&quality=90",
      "position": "C",
      "classYear": "Sophomore",
      "height": "5-11",
      "weight": "190",
      "bats": "R",
      "throws": "R",
      "hometown": "Sylmar, Calif.",
      "from": "Sylmar, Calif.",
      "lastSchool": null,
      "previousSchool": "Long Beach State",
      "previousSchools": [
        "Long Beach State"
      ],
      "sourceFields": {
        "B/T": "R/R",
        "Class": "Sophomore",
        "Hometown": "Sylmar, Calif.",
        "Ht./Wt.": "5-11 / 190",
        "Major": "Sociology",
        "Position": "C",
        "Prev School": "Long Beach State"
      }
    },
    {
      "key": "https://ucirvinesports.com/sports/baseball/roster/alex-umland/7610",
      "profileUrl": "https://ucirvinesports.com/sports/baseball/roster/alex-umland/7610",
      "name": "Alex Umland",
      "firstName": "Alex",
      "lastName": "Umland",
      "number": "55",
      "photoUrl": "https://ucirvinesports.com/images/2025/10/9/55umland26.jpg?width=80&quality=90",
      "position": "RHP",
      "classYear": "Redshirt Freshman",
      "height": "6-4",
      "weight": "220",
      "bats": "R",
      "throws": "R",
      "hometown": "Los Angeles, Calif.",
      "from": "Los Angeles, Calif.",
      "lastSchool": null,
      "previousSchool": "University of Oregon",
      "previousSchools": [
        "University of Oregon"
      ],
      "sourceFields": {
        "B/T": "R/R",
        "Class": "Redshirt Freshman",
        "Hometown": "Los Angeles, Calif.",
        "Ht./Wt.": "6-4 / 220",
        "Major": "Sociology",
        "Position": "RHP",
        "Prev School": "University of Oregon"
      }
    }
  ]
}